Metadata-Version: 2.1
Name: maminbot
Version: 0.1.8
Summary: Bots that write like members of the Mamin family.
Author: Harrison Mamin
Author-email: harrisonmamin@gmail.com
